macpyver_core/__init__.py
macpyver_core/macpyver.py
macpyver_core/model.py
macpyver_core/py.typed
macpyver_core/version_source.py
macpyver_core-1.0.0.dist-info/LICENSE.md
macpyver_core-1.0.0.dist-info/METADATA
macpyver_core-1.0.0.dist-info/WHEEL
macpyver_core-1.0.0.dist-info/RECORD
